profilegraph.py
profilegraph-0.2.0.dist-info/LICENSE
profilegraph-0.2.0.dist-info/WHEEL
profilegraph-0.2.0.dist-info/METADATA
profilegraph-0.2.0.dist-info/RECORD
