Metadata-Version: 2.1
Name: profilegraph
Version: 0.2.0
Summary: IPython magic for cProfile graphs w gprof2dot and graphviz in Jupyter/iterm.
Home-page: https://github.com/stefco/profilegraph
License: UNKNOWN
Author: Stefan Countryman
Author-email: stefan.countryman@gmail.com
Requires-Python: >=3.6
Classifier: License :: OSI Approved :: GNU General Public License v3 or later (GPLv3+)
Requires-Dist: gprof2dot
Requires-Dist: flit ; extra == "dev"
Requires-Dist: ipython ; extra == "ipy"
Requires-Dist: pytest ; extra == "test"
Provides-Extra: dev
Provides-Extra: ipy
Provides-Extra: test
